glyphspkg/__init__.py
glyphspkg/_version.py
glyphspkg/cmdline.py
glyphspkg/filenames.py
glyphspkg/package_to_single.py
glyphspkg/paths.py
glyphspkg/plist.py
glyphspkg/single_to_package.py
glyphspkg-0.2.1.dist-info/LICENSE
glyphspkg-0.2.1.dist-info/METADATA
glyphspkg-0.2.1.dist-info/WHEEL
glyphspkg-0.2.1.dist-info/entry_points.txt
glyphspkg-0.2.1.dist-info/top_level.txt
glyphspkg-0.2.1.dist-info/RECORD
