Metadata-Version: 2.1
Name: glyphspkg
Version: 0.2.1
Summary: Converter from .glyphspackage to .glyphs files and vice versa
Home-page: https://github.com/jenskutilek/glyphspkg
Author: Jens Kutilek
License: MIT
Project-URL: Documentation, https://github.com/jenskutilek/glyphspkg
Project-URL: Source, https://github.com/jenskutilek/glyphspkg
Project-URL: Tracker, https://github.com/jenskutilek/glyphspkg/issues
Classifier: Programming Language :: Python :: 3
Classifier: License :: OSI Approved :: MIT License
Classifier: Operating System :: OS Independent
Classifier: Environment :: Console
Classifier: Topic :: Multimedia :: Graphics
Classifier: Topic :: Multimedia :: Graphics :: Graphics Conversion
Classifier: Topic :: Multimedia :: Graphics :: Editors :: Vector-Based
Requires-Python: >=3.8
License-File: LICENSE
Requires-Dist: openstep-plist>=0.4.0
